trvaep/__init__.py
trvaep/data_loader.py
trvaep/pl.py
trvaep/utils.py
trvaep/model/__init__.py
trvaep/model/_cvae.py
trvaep/model/_losses.py
trvaep/model/helper_module.py
trvaep/model/train.py
trvaep/model/utiil.py
trvaep-0.1.0.dist-info/LICENSE
trvaep-0.1.0.dist-info/WHEEL
trvaep-0.1.0.dist-info/METADATA
trvaep-0.1.0.dist-info/RECORD
