Metadata-Version: 2.1
Name: trvaep
Version: 0.1.0
Summary: trVAE - Transfer Variational Autoencoders pytorch
Home-page: UNKNOWN
License: UNKNOWN
Author: Mohammad Lotfollahi
Author-email: mohammad.lotfollahi@helmholtz-muenchen.de
Classifier: License :: OSI Approved :: MIT License
Requires-Dist: future-fstrings
Requires-Dist: get_version
Requires-Dist: get_version
Requires-Dist: scanpy
Requires-Dist: adjustText
Requires-Dist: torch
Requires-Dist: torchvision
Requires-Dist: numpy
Requires-Dist: scipy
Requires-Dist: seaborn
Requires-Dist: matplotlib
Requires-Dist: pandas
Requires-Dist: pytest; extra == "test"
Provides-Extra: test
